{
  "provinces": [
	{ "provinceId": 0, "name": "Ulster", "neighbors": [1, 16,14,33,32,10,15],"coastal": true},
	{ "provinceId": 1, "name": "Connacht", "neighbors": [0, 4, 5, 10, 33, 55, 69],"coastal": true },
	{ "provinceId": 2, "name": "Leinster", "neighbors": [ 8, 4,9,5],"coastal": true },
	{ "provinceId": 3, "name": "Munster", "neighbors": [ 66,6,49],"coastal": true },

	{ "provinceId": 4, "name": "Cornwall", "neighbors": [5, 69, 2],"coastal": true },
	{ "provinceId": 5, "name": "Wessex", "neighbors": [1,4, 55, 45,2,8] },
	{ "provinceId": 6, "name": "Kent", "neighbors": [ 7, 11,3,8] },
	{ "provinceId": 7, "name": "Essex", "neighbors": [6, 8, 49,46, 44, 48] },
	{ "provinceId": 8, "name": "East Anglia", "neighbors": [7, 45,2, 44,6,5] },
	{ "provinceId": 9, "name": "Mercia", "neighbors": [11, 70,12,2] },
	{ "provinceId": 10, "name": "Northumbria", "neighbors": [1, 13, 14, 69,0] },

	{ "provinceId": 11, "name": "Gwynedd", "neighbors": [ 70, 66,67,6],"coastal": true },
	{ "provinceId": 12, "name": "Powys", "neighbors": [9, 67] },

	{ "provinceId": 13, "name": "Cumbria", "neighbors": [10, 14, 17] },
	{ "provinceId": 14, "name": "Lothian", "neighbors": [10, 13,0,16] },
	{ "provinceId": 15, "name": "Galloway", "neighbors": [ 16,26,24,32,0, 25] },
	{ "provinceId": 16, "name": "Strathclyde", "neighbors": [15, 17,14,25] },
	{ "provinceId": 17, "name": "Fife", "neighbors": [16, 18,25, 13,19],"coastal": true },
	{ "provinceId": 18, "name": "Alba", "neighbors": [17, 19],"coastal": true },
	{ "provinceId": 19, "name": "Moray", "neighbors": [18,25,22,17],"coastal": true },
	{ "provinceId": 20, "name": "The Greyfells", "neighbors": [19, 21, 22],"coastal": true },
	{ "provinceId": 21, "name": "Silvermere", "neighbors": [20, 22, 23,27] },
	{ "provinceId": 22, "name": "Barrowlands", "neighbors": [20, 21, 24, 25,19],"coastal": true },
	{ "provinceId": 23, "name": "Sunstone Hills", "neighbors": [21, 27,29,28],"coastal": true },
	{ "provinceId": 24, "name": "Dragon's Tooth", "neighbors": [22, 25, 27,26,30,15] },
	{ "provinceId": 25, "name": "The Gloomfen", "neighbors": [22, 24, 17,19, 15, 16] },
	{ "provinceId": 26, "name": "Ostengard", "neighbors": [ 30,15,24,31,32] },
	{ "provinceId": 27, "name": "Westmarch", "neighbors": [23, 24, 28,21,30] },
	{ "provinceId": 28, "name": "Blackfen", "neighbors": [27, 29, 36,23,57,30] },
	{ "provinceId": 29, "name": "The Sunken Isles", "neighbors": [28,57,23],"coastal": true },
	{ "provinceId": 30, "name": "Kingsfall", "neighbors": [26, 31, 35,36,27,24,28] },
	{ "provinceId": 31, "name": "Whisper wood", "neighbors": [30, 32,35,34,26] },
	{ "provinceId": 32, "name": "The Verdant Valley", "neighbors": [31, 33, 34,26,15,0] },
	{ "provinceId": 33, "name": "Amber Peaks", "neighbors": [32, 34,0,1,55,54,42] },
	{ "provinceId": 34, "name": "Frostwind Pass", "neighbors": [32, 33, 35,31, 42] },
	{ "provinceId": 35, "name": "Stonehearth", "neighbors": [30, 34, 36, 40, 41, 42,31] },
	{ "provinceId": 36, "name": "Serpent's Spine", "neighbors": [35,57,60,28,30,40,43] },
	{ "provinceId": 37, "name": "Shadow march", "neighbors": [ 38, 42, 50, 53, 41] },
	{ "provinceId": 38, "name": "Goldengrove", "neighbors": [37, 50,51,53,52, 44] },
	{ "provinceId": 39, "name": "Sun's Reach", "neighbors": [65,47],"coastal": true },
	{ "provinceId": 40, "name": "Ironoath Peaks", "neighbors": [35, 41, 43,36] },
	{ "provinceId": 41, "name": "The Salt Wastes", "neighbors": [35, 40, 42, 37] },
	{ "provinceId": 42, "name": "The Riverlands", "neighbors": [35, 37, 41, 33,54, 53, 34],"coastal": true },
	{ "provinceId": 43, "name": "Winter's Grasp", "neighbors": [40, 36,60,62] },
	{ "provinceId": 44, "name": "The Greenwold", "neighbors": [45, 46, 38, 7, 8, 51, 52] },
	{ "provinceId": 45, "name": "Sundered Coast", "neighbors": [8, 44, 52, 55, 5],"coastal": true },
	{ "provinceId": 46, "name": "The Heartlands", "neighbors": [44, 47, 48,51,7] },
	{ "provinceId": 47, "name": "The Ghostwater", "neighbors": [46, 48, 51,39],"coastal": true },
	{ "provinceId": 48, "name": "Dornwood", "neighbors": [46, 47, 49, 7] },
	{ "provinceId": 49, "name": "The Silent Glade", "neighbors": [48,7,3] },
	{ "provinceId": 50, "name": "Tanglewood", "neighbors": [ 38,64, 37] },
	{ "provinceId": 51, "name": "The High Moors", "neighbors": [47, 64,38,46, 44] },
	{ "provinceId": 52, "name": "Redwater Crossing", "neighbors": [53, 54,38, 45, 44] },
	{ "provinceId": 53, "name": "Dragon's Maw", "neighbors": [52, 54,38,37, 42] },
	{ "provinceId": 54, "name": "The Azure Coast", "neighbors": [52, 53, 55,33,42],"coastal": true },
	{ "provinceId": 55, "name": "Whispering Plains", "neighbors": [54, 5,33, 45, 1],"coastal": true },
	{ "provinceId": 56, "name": "Raven's Perch", "neighbors": [57, 58] },
	{ "provinceId": 57, "name": "The Icevein Peaks", "neighbors": [56,36,58,59,29,28] },
	{ "provinceId": 58, "name": "The Broken Steppes", "neighbors": [56, 57,59] },
	{ "provinceId": 59, "name": "Blackwood Forest", "neighbors": [58, 60,57] },
	{ "provinceId": 60, "name": "The Crystal Fens", "neighbors": [59, 61, 62,36,43] },
	{ "provinceId": 61, "name": "The Golden Plains", "neighbors": [60, 62] },
	{ "provinceId": 62, "name": "Emberfall", "neighbors": [60, 61, 64,43,63] },
	{ "provinceId": 63, "name": "Sundown Vale", "neighbors": [62,64] },
	{ "provinceId": 64, "name": "Starfall Peninsula", "neighbors": [62, 65, 63,50,51],"coastal": true },
	{ "provinceId": 65, "name": "Shimmering Isles", "neighbors": [64,39],"coastal": true },
	{ "provinceId": 66, "name": "The Howling Wastes", "neighbors": [3,11,67],"coastal": true },
	{ "provinceId": 67, "name": "Dragon's Graveyard", "neighbors": [12,66,11,70] },
	{ "provinceId": 68, "name": "The Cinderlands", "neighbors": [69] },
	{ "provinceId": 69, "name": "Obsidian Fields", "neighbors": [68, 4, 10, 1],"coastal": true },
	{ "provinceId": 70, "name": "Rockside", "neighbors": [9, 11, 67],"coastal": true }
  ]
}
